psifx/__init__.py
psifx/command.py
psifx/tool.py
psifx/audio/__init__.py
psifx/audio/command.py
psifx/audio/tool.py
psifx/audio/diarization/__init__.py
psifx/audio/diarization/command.py
psifx/audio/diarization/tool.py
psifx/audio/diarization/pyannote/__init__.py
psifx/audio/diarization/pyannote/command.py
psifx/audio/diarization/pyannote/tool.py
psifx/audio/identification/__init__.py
psifx/audio/identification/command.py
psifx/audio/identification/tool.py
psifx/audio/identification/pyannote/__init__.py
psifx/audio/identification/pyannote/command.py
psifx/audio/identification/pyannote/tool.py
psifx/audio/manipulation/__init__.py
psifx/audio/manipulation/command.py
psifx/audio/manipulation/tool.py
psifx/audio/speech/__init__.py
psifx/audio/speech/command.py
psifx/audio/speech/tool.py
psifx/audio/speech/opensmile/__init__.py
psifx/audio/speech/opensmile/command.py
psifx/audio/speech/opensmile/tool.py
psifx/audio/transcription/__init__.py
psifx/audio/transcription/command.py
psifx/audio/transcription/tool.py
psifx/audio/transcription/whisper/__init__.py
psifx/audio/transcription/whisper/command.py
psifx/audio/transcription/whisper/tool.py
psifx/io/__init__.py
psifx/io/csv.py
psifx/io/json.py
psifx/io/rttm.py
psifx/io/tar.py
psifx/io/txt.py
psifx/io/video.py
psifx/io/vtt.py
psifx/io/wav.py
psifx/io/yaml.py
psifx/text/__init__.py
psifx/text/command.py
psifx/text/tool.py
psifx/text/chat/__init__.py
psifx/text/chat/command.py
psifx/text/chat/tool.py
psifx/text/instruction/__init__.py
psifx/text/instruction/command.py
psifx/text/instruction/tool.py
psifx/text/llm/__init__.py
psifx/text/llm/command.py
psifx/text/llm/tool.py
psifx/text/llm/anthropic/__init__.py
psifx/text/llm/anthropic/tool.py
psifx/text/llm/hf/__init__.py
psifx/text/llm/hf/tool.py
psifx/text/llm/ollama/__init__.py
psifx/text/llm/ollama/tool.py
psifx/text/llm/openai/__init__.py
psifx/text/llm/openai/tool.py
psifx/utils/__init__.py
psifx/utils/command.py
psifx/utils/draw.py
psifx/video/__init__.py
psifx-0.2.0.dist-info/licenses/LICENSE
psifx-0.2.0.dist-info/METADATA
psifx-0.2.0.dist-info/WHEEL
psifx-0.2.0.dist-info/entry_points.txt
psifx-0.2.0.dist-info/top_level.txt
psifx-0.2.0.dist-info/RECORD
