Metadata-Version: 2.4
Name: psifx
Version: 0.2.0
Summary: Psychological and Social Interactions Feature Extraction
Author-email: Guillaume Rochette <guillaume.rochette@unil.ch>, Matthew Vowels <matthew.vowels@unil.ch>, Mathieu Rochat <mathieu.louis.rochat@gmail.com>
Project-URL: homepage, https://github.com/psifx/psifx
Project-URL: documentation, https://psifx.github.io/psifx/
Project-URL: repository, https://github.com/psifx/psifx
Keywords: video,audio,language,machine-learning,pipeline,multimodal
Classifier: Development Status :: 3 - Alpha
Classifier: License :: OSI Approved :: Apache Software License
Classifier: Operating System :: OS Independent
Classifier: Programming Language :: Python :: 3
Requires-Python: >=3.10
License-File: LICENSE
Requires-Dist: whisperx
Requires-Dist: opensmile
Requires-Dist: pyannote.audio
Requires-Dist: pydub
Requires-Dist: speechbrain
Requires-Dist: absolutely-not-scikit-video
Requires-Dist: ffmpeg-python
Requires-Dist: mediapipe
Requires-Dist: absolutely-not-samurai
Requires-Dist: ultralytics
Requires-Dist: torch
Requires-Dist: torchvision
Requires-Dist: torchaudio
Requires-Dist: accelerate
Requires-Dist: bitsandbytes
Requires-Dist: transformers>=4.41.0
Requires-Dist: huggingface_hub
Requires-Dist: langchain
Requires-Dist: langchain-community
Requires-Dist: langchain-anthropic
Requires-Dist: langchain-openai
Requires-Dist: langchain-ollama
Requires-Dist: ollama
Requires-Dist: matplotlib<=3.8.4
Requires-Dist: nltk
Requires-Dist: platformdirs
Requires-Dist: tqdm
Requires-Dist: loguru
Requires-Dist: decord
Provides-Extra: docs
Requires-Dist: furo; extra == "docs"
Requires-Dist: myst_parser; extra == "docs"
Requires-Dist: sphinx; extra == "docs"
Requires-Dist: sphinx-argparse; extra == "docs"
Requires-Dist: sphinx-copybutton; extra == "docs"
Requires-Dist: sphinx-autodoc-typehints; extra == "docs"
Requires-Dist: sphinxcontrib-napoleon; extra == "docs"
Requires-Dist: sphinxcontrib-autoprogram; extra == "docs"
Requires-Dist: snowballstemmer<=2.2.0; extra == "docs"
Provides-Extra: dev
Requires-Dist: pytest>=8.0.0; extra == "dev"
Requires-Dist: pytest-cov>=6.0.0; extra == "dev"
Requires-Dist: rapidfuzz; extra == "dev"
Dynamic: license-file
